ch_json_logger/__init__.py
ch_json_logger/json_logger.py
ch_json_logger-1.1.4.dist-info/DESCRIPTION.rst
ch_json_logger-1.1.4.dist-info/METADATA
ch_json_logger-1.1.4.dist-info/RECORD
ch_json_logger-1.1.4.dist-info/WHEEL
ch_json_logger-1.1.4.dist-info/metadata.json
ch_json_logger-1.1.4.dist-info/top_level.txt
