Metadata-Version: 2.0
Name: ch-json-logger
Version: 1.1.4
Summary: JSON logger for python
Home-page: https://bitbucket.org/sfilatov96/python-json-logger
Author: Stepan Filatov
Author-email: stepa-filatov@yandex.ru
License: Apache 2.0
Keywords: json logger python flask development kibana
Platform: UNKNOWN
Classifier: Development Status :: 5 - Production/Stable
Classifier: License :: OSI Approved :: Apache Software License
Classifier: Intended Audience :: Developers
Classifier: Topic :: Software Development :: Libraries :: Python Modules
Classifier: Topic :: Utilities
Classifier: Programming Language :: Python :: 3.5
Classifier: Programming Language :: Python :: 3.6
Requires-Python: >=3.5
Requires-Dist: JSON-log-formatter (>=0.2.0)
